sm_ai_pose_generator/__init__.py
sm_ai_pose_generator-1767000.207.312.dist-info/licenses/LICENSE
sm_ai_pose_generator-1767000.207.312.dist-info/METADATA
sm_ai_pose_generator-1767000.207.312.dist-info/WHEEL
sm_ai_pose_generator-1767000.207.312.dist-info/top_level.txt
sm_ai_pose_generator-1767000.207.312.dist-info/RECORD
